<MimamoriModule>
    <Setup>

        <ChecksumCalculationMethod>Isuzu</ChecksumCalculationMethod>
        <CheckSumLength>2</CheckSumLength>
        <DataStartIndex>0</DataStartIndex>
        <DataHeaderLength>0</DataHeaderLength>
        <DtcStartIndex>2</DtcStartIndex>
		<ModuleResponseDelay>300</ModuleResponseDelay>
		<ModuleResponseEndDelay>50</ModuleResponseEndDelay>
        <NegativeResponseCodeIndex>0</NegativeResponseCodeIndex>
        <NegativeResponseValue>0</NegativeResponseValue>
		<NumberOfRetries>2</NumberOfRetries>
        <SentMessageIdentifierIndex>0</SentMessageIdentifierIndex>
        <ValidateChecksum>True</ValidateChecksum>
        <ValidResponseOffset>0</ValidResponseOffset>
        <ModuleKeepAliveTime>200</ModuleKeepAliveTime>
        <KeepAliveResponseRequired>No</KeepAliveResponseRequired>
        <KeepAlivePriority>10</KeepAlivePriority>

        <Communication>
            <Debug>Off</Debug>
            <Name>Mimamori</Name>
            <BufferSize>4096</BufferSize>
            <CommSize>1</CommSize>
            <Timeout>10000</Timeout>
            <Retries>7</Retries>
        </Communication>

        <Logging>
            <Status>Enabled</Status>
            <ProcessName>MimamoriModule</ProcessName>
            <AdditionalLogFile>/Communication/MimamoriModule.log</AdditionalLogFile>
            <Debug>Off</Debug>
            <LocalEcho>Disabled</LocalEcho>
            <Verbose>0x3F</Verbose>
        </Logging>
    </Setup>



    <SerialMessages>
        <!-- ============ Message Table ============ -->
        <VehicleMessages>

            <ClearFaults>
                <TransmitMessage>DtcClearRequest</TransmitMessage>
                <TransmitInterpretation/>
                <ReplyMessage>DtcClearTriggerNotification</ReplyMessage>              
                <ReplyInterpretation>DtcsCleared</ReplyInterpretation>
            </ClearFaults>

            <ClearHistory>
                <TransmitMessage>ClearHistoryRequest</TransmitMessage>
                <TransmitInterpretation/>
                <ReplyMessage>ClearHistoryNotification</ReplyMessage>
                <ReplyInterpretation>HistoryCleared</ReplyInterpretation>
            </ClearHistory>

            <ConnectingDevBcast>
                <TransmitMessage>ConnectingDevInfo</TransmitMessage>
                <TransmitInterpretation/>
                <ReplyMessage>ConnectingDevBcast</ReplyMessage>
                <ReplyInterpretation/>
            </ConnectingDevBcast>

            <ConnectingDeviceInfo>
                <TransmitMessage>ConnectingDevInfo</TransmitMessage>
                <TransmitInterpretation/>
                <ReplyMessage>CurrentTimeNotification</ReplyMessage>
                <ReplyInterpretation/>
            </ConnectingDeviceInfo>

            <CurrentTimeResponse>
                <TransmitMessage>CurrentTimeResponse</TransmitMessage>
                <TransmitInterpretation/>
                <ReplyMessage>VehicleAttributeInfo</ReplyMessage>
                <ReplyInterpretation>EngineType</ReplyInterpretation>
            </CurrentTimeResponse>

            <ModuleKeepAlive>
                <TransmitMessage>ModuleKeepAlive</TransmitMessage>
                <TransmitInterpretation/>
                <ReplyMessage>ModuleKeepAlive</ReplyMessage>
                <ReplyInterpretation/>
            </ModuleKeepAlive>

            <ReadFaults>
                <TransmitMessage>DtcCheckRequest</TransmitMessage>
                <TransmitInterpretation/>
                <ReplyMessage>DtcCheckResponse</ReplyMessage>
                <ReplyInterpretation/>
            </ReadFaults>

            <TriggerSetup>
                <TransmitMessage>TotalMileageTrigger</TransmitMessage>
                <TransmitInterpretation/>
                <ReplyMessage>VehicleNumberNotification</ReplyMessage>
                <ReplyInterpretation/>
            </TriggerSetup>

            <ReadTotalMileage>
                <TransmitMessage>TotalMileageResponse</TransmitMessage>
                <TransmitInterpretation/>
                <ReplyMessage>TotalMileageNotification</ReplyMessage>
                <ReplyInterpretation>TotalMileageInterp</ReplyInterpretation>
            </ReadTotalMileage>

            <ReadFuelEconomy>
                <TransmitMessage>FuelEconomyResponse</TransmitMessage>
                <TransmitInterpretation/>
                <ReplyMessage>TotalMileageNotification</ReplyMessage>
                <ReplyInterpretation>FuelEconomyInterp</ReplyInterpretation>
            </ReadFuelEconomy>

            <ReadDrmEngine>
                <TransmitMessage>DrmEngineResponse</TransmitMessage>
                <TransmitInterpretation/>
                <ReplyMessage>TriggerConfirmationNotification</ReplyMessage>
                <ReplyInterpretation>DrmEngineInterp</ReplyInterpretation>
            </ReadDrmEngine>

            <ReadDrmAt>
                <TransmitMessage>DrmAtResponse</TransmitMessage>
                <TransmitInterpretation/>
                <ReplyMessage>TriggerConfirmationNotification</ReplyMessage>
                <ReplyInterpretation>DrmAtInterp</ReplyInterpretation>
            </ReadDrmAt>

            <ReadDrmScr>
                <TransmitMessage>DrmScrResponse</TransmitMessage>
                <TransmitInterpretation/>
                <ReplyMessage>TriggerConfirmationNotification</ReplyMessage>
                <ReplyInterpretation>DrmScrInterp</ReplyInterpretation>
            </ReadDrmScr>

            <ReadDrmBrake>
                <TransmitMessage>DrmBrakeResponse</TransmitMessage>
                <TransmitInterpretation/>
                <ReplyMessage>TriggerConfirmationNotification</ReplyMessage>
                <ReplyInterpretation>DrmBrakeInterp</ReplyInterpretation>
            </ReadDrmBrake>

            <ReadDrmEdrOilTemp>
                <TransmitMessage>DrmEdrOilTempResponse</TransmitMessage>
                <TransmitInterpretation/>
                <ReplyMessage>DrmEdrOilNotification</ReplyMessage>
                <ReplyInterpretation>DrmEdrOilTempInterp</ReplyInterpretation>
            </ReadDrmEdrOilTemp>

            <VehicleAttributeResponse>
                <TransmitMessage>VehicleAttributeResponse</TransmitMessage>
                <TransmitInterpretation/>
                <ReplyMessage>VehicleNumberNotification</ReplyMessage>
                <ReplyInterpretation/>
            </VehicleAttributeResponse>

            <VehicleNumberResponse>
                <TransmitMessage>VehicleNumberResponse</TransmitMessage>
                <TransmitInterpretation/>
                <ReplyMessage>VehicleNumberNotification</ReplyMessage>
                <ReplyInterpretation/>
            </VehicleNumberResponse>

            <ReadTriggerResponse>
                <TransmitMessage>ReadTriggerResponse</TransmitMessage>
                <TransmitInterpretation/>
                <ReplyMessage>ReadTriggerResponseNotification</ReplyMessage>
                <ReplyInterpretation/>
            </ReadTriggerResponse>

        </VehicleMessages>


        <!-- ============ Message Formats ============ -->
        <TransmitMessages>
            <!--ConnectingDevInfo>0x31,0x00,0x00,0x08,0x??,0x??,0x??,0x??,0x??,0x??</ConnectingDevInfo-->
            <ConnectingDevInfo>0x31,0x00,0x00,0x08,0x00,0x00,0x00,0x00,0x00,0x00</ConnectingDevInfo>
            <CurrentTimeResponse>0x31,0x0F,0x00</CurrentTimeResponse>
            <ModuleKeepAlive>0x31,0x00,0x00,0x08,0x00,0x00,0x00,0x00,0x00,0x00</ModuleKeepAlive>
            <DtcCheckRequest>0x31,0x0B,0x00,0x01,0x03,0x01,0x00,0xFF,0x94,0x00,0x6C</DtcCheckRequest>
            <DtcClearRequest>0x31,0x0B,0x00,0x01,0x03,0x01,0x00,0x00,0x00,0x00,0x00</DtcClearRequest>
            <ClearHistoryRequest>0x31,0x0B,0x00,0x01,0x10,0x01,0x0F</ClearHistoryRequest>
            <!--TriggerSetup>0x31,0x0B,0x00,0x07,0x32,0x01,0x01,0x00,0x02,0x02,0x00,0x03,0x06,0x00,0x04,0x84,0x00,0x05,0xC1,0x00,0x06,0xC2,0x00,0x07,0xC3,0x00</TriggerSetup-->
            <TotalMileageTrigger>0x31,0x0B,0x00,0x01,0x03,0x01,0x00,0x48,0x00,0x04,0x04</TotalMileageTrigger>
            <TotalMileageResponse>0x31,0x0B,0x00,0x01,0x03,0x01,0x00,0x48,0x00,0x04,0x04</TotalMileageResponse>
            <TotalFuelConsumptionTrigger>0x31,0x0B,0x00,0x01,0x03,0x01,0x00,0x48,0x00,0x14,0x04</TotalFuelConsumptionTrigger>
            <FuelEconomyResponse>0x31,0x0B,0x00,0x01,0x03,0x01,0x00,0x48,0x00,0x14,0x04</FuelEconomyResponse>
            <DrmEngineResponse>0x31,0x0B,0x00,0x01,0x03,0x01,0x00,0x42,0x00,0x00,0x14</DrmEngineResponse>
            <DrmAtResponse>0x31,0x0B,0x00,0x01,0x03,0x01,0x00,0x43,0x51,0xBC,0x14</DrmAtResponse>
            <DrmScrResponse>0x31,0x0B,0x00,0x01,0x03,0x01,0x00,0x44,0xBB,0x9C,0x14</DrmScrResponse>
            <DrmBrakeResponse>0x31,0x0B,0x00,0x01,0x03,0x01,0x00,0x45,0x66,0x78,0x14</DrmBrakeResponse>
            <DrmEdrOilTempResponse>0x31,0x0B,0x00,0x01,0x03,0x01,0x00,0x46,0xE1,0x8C,0x10</DrmEdrOilTempResponse>
            <DrmEngine>0x31,0x0B,0x00,0x01,0x03,0x01,0x00,0x42,0x00,0x00,0x16</DrmEngine>
            <DrmAt>0x31,0x0B,0x00,0x01,0x03,0x01,0x00,0x43,0x51,0xBC,0x16</DrmAt>
            <DrmScr>0x31,0x0B,0x00,0x01,0x03,0x01,0x00,0x44,0xBB,0x9C,0x16</DrmScr>
            <DrmBrake>0x31,0x0B,0x00,0x01,0x03,0x01,0x00,0x45,0x66,0x78,0x16</DrmBrake>
            <DrmEdrOilTemp>0x31,0x0B,0x00,0x01,0x03,0x01,0x00,0x46,0xE1,0x8C,0x10</DrmEdrOilTemp>
            <Dtc>0x31,0x0B,0x00,0x01,0x03,0x01,0x00,0xFF,0x94,0x00,0x6C</Dtc>
            <VehicleAttributeResponse>0x31,0x0C,0x00,0x00,0x00</VehicleAttributeResponse>
            <VehicleNumberResponse>0x31,0x04,0x00,0x00,0x26</VehicleNumberResponse>
            <ReadTriggerResponse>0x31,0x0A,0x00,0x0C</ReadTriggerResponse>
        </TransmitMessages>


        <!-- ============ Message PIDs/LIDs ============ -->
        <TransmitInterpretations>
        </TransmitInterpretations>


        <!-- ============ Message Responses ============ -->
        <ReplyMessages>

            <ConnectingDevBcast>
                <Reply>0x02,0x00,0x17,0x80,0x16,0x00,0x00,0x00,0x00,0x31,0x00,0x??,0x00,0x0A,0xFE,0xF0,0x01,0x??,0x??,0x??,0x??,0x??,0x??,0x??,0x03,0x??,0x??</Reply>
                <!--Reply>0x01,0x01,0x01,0x00,0x80,0x??,0x60,0x8F,0x20,0x00,0x00,0x0F,0xA1,0x??</Reply-->
            </ConnectingDevBcast>

            <CurrentTimeNotification>
                <Reply>0x02,0x00,0x17,0x80,0x13,0x00,0x00,0x00,0x00,0x31,0x0F,0x??,0x00,0x07,0x??,0x??,0x??,0x??,0x??,0x??,0x??,0x03,0x??,0x??</Reply>
            </CurrentTimeNotification>

            <ModuleKeepAlive>
                <Reply>0x02,0x00,0x17,0x80,0x13,0x00,0x00,0x00,0x00,0x31,0x0F,0x??,0x00,0x07,0x??,0x??,0x??,0x??,0x??,0x??,0x??,0x03,0x??,0x??</Reply>
            </ModuleKeepAlive>

            <ClearHistoryNotification>
                <Reply>0x02,0x00,0x17,0x80,0x??,0x00,0x00,0x00,0x00,0x31,0x0B,0x??,0x??,0x??,0x??,0x03,0x??,0x??</Reply>
            </ClearHistoryNotification>  

            <DtcCheckResponse>
                <Reply>0x02,0x00,0x17,0x80,0x??,0x00,0x00,0x00,0x00,0x31,0x0A,0x??,0x00,0x??,0x03,0x01,0x??,0x??,0x??,0x??,0x??,0x??,0x??,0x??,0x??,0x??,0x??,0x??,0x??,0x??,0x??,0x??,0x??,0x??,0x??,0x??,0x??,0x??,0x??,0x??,0x??,0x??,0x??,0x??,0x??,0x??,0x??,0x??,0x??,0x??,0x??,0x??,0x??,0x??,0x??,0x??,0x??,0x??,0x??,0x??,0x??,0x??,0x??,0x??,0x??,0x??,0x??,0x??,0x??,0x??,0x??,0x??,0x??,0x??,0x??,0x??,0x??,0x??,0x??,0x??,0x??,0x??,0x??,0x??,0x??,0x??,0x??,0x??,0x??,0x??,0x??,0x??,0x??,0x??,0x??,0x??,0x??,0x??,0x??,0x??,0x??,0x??,0x??,0x??,0x??,0x??,0x??,0x??,0x??,0x??,0x??,0x??,0x??,0x??,0x??,0x??,0x??,0x??,0x??,0x??,0x??,0x??,0x??,0x??,0x03,0x??,0x??</Reply>
            </DtcCheckResponse>                                                                                

            <DtcClearTriggerNotification>
                <Reply>0x02,0x00,0x17,0x80,0x??,0x00,0x00,0x00,0x00,0x31,0x0A,0x??,0x??,0x??,0x??,0x??,0x03,0x??,0x??</Reply>              
            </DtcClearTriggerNotification>                                                               

            <TotalMileageNotification>
                <Reply>0x02,0x00,0x17,0x80,0x??,0x00,0x00,0x00,0x00,0x31,0x0A,0x??,0x??,0x??,0x??,0x??,0x??,0x??,0x??,0x??,0x03,0x??,0x??</Reply>
            </TotalMileageNotification>                                                                       

            <TriggerConfirmationNotification>
                <Reply>0x02,0x00,0x17,0x80,0x??,0x00,0x00,0x00,0x00,0x31,0x0A,0x??,0x??,0x??,0x??,0x??,0x??,0x??,0x??,0x??,0x??,0x??,0x??,0x??,0x??,0x??,0x??,0x??,0x??,0x??,0x??,0x??,0x??,0x??,0x??,0x??,0x03,0x??,0x??</Reply>
            </TriggerConfirmationNotification>                                                           

            <DrmEdrOilNotification>
                <Reply>0x02,0x00,0x17,0x80,0x??,0x00,0x00,0x00,0x00,0x31,0x0A,0x??,0x??,0x??,0x??,0x??,0x??,0x??,0x??,0x??,0x??,0x??,0x??,0x??,0x??,0x??,0x??,0x??,0x??,0x??,0x??,0x??,0x03,0x??,0x??</Reply>
            </DrmEdrOilNotification> 

            <VehicleAttributeInfo>
                <Reply>0x02,0x00,0x17,0x80,0x84,0x00,0x00,0x00,0x00,0x31,0x0C,0x??,0x00,0x78,0x??,0x??,0x??,0x??,0x??,0x??,0x??,0x??,0x??,0x??,0x??,0x??,0x??,0x??,0x??,0x??,0x??,0x??,0x??,0x??,0x??,0x??,0x??,0x??,0x??,0x??,0x??,0x??,0x??,0x??,0x??,0x??,0x??,0x??,0x??,0x??,0x??,0x??,0x??,0x??,0x??,0x??,0x??,0x??,0x??,0x??,0x??,0x??,0x??,0x??,0x??,0x??,0x??,0x??,0x??,0x??,0x??,0x??,0x??,0x??,0x??,0x??,0x??,0x??,0x??,0x??,0x??,0x??,0x??,0x??,0x??,0x??,0x??,0x??,0x??,0x??,0x??,0x??,0x??,0x??,0x??,0x??,0x??,0x??,0x??,0x??,0x??,0x??,0x??,0x??,0x??,0x??,0x??,0x??,0x??,0x??,0x??,0x??,0x??,0x??,0x??,0x??,0x??,0x??,0x??,0x??,0x??,0x??,0x??,0x??,0x??,0x??,0x??,0x??,0x??,0x??,0x??,0x??,0x??,0x??,0x03,0x??,0x??</Reply>
            </VehicleAttributeInfo>                                                                            

            <VehicleNumberNotification>
                <Reply>0x02,0x00,0x17,0x??,0x32,0x00,0x00,0x00,0x00,0x31,0x04,0x??,0x00,0x26,0x00,0x24,0x??,0x??,0x??,0x??,0x??,0x??,0x??,0x??,0x??,0x??,0x??,0x??,0x??,0x??,0x??,0x??,0x??,0x??,0x??,0x??,0x??,0x??,0x??,0x??,0x??,0x??,0x??,0x??,0x??,0x??,0x??,0x??,0x??,0x??,0x??,0x??,0x03,0x??,0x??</Reply>
            </VehicleNumberNotification>

            <ReadTriggerResponseNotification>
                <Reply>0x02,0x00,0x17,0x80,0x??,0x00,0x00,0x00,0x00,0x31,0x0B,0x??,0x??,0x??,0x??,0x03,0x??,0x??</Reply>
            </ReadTriggerResponseNotification>
        </ReplyMessages>


        <!-- ============ Data Translations ============ -->
        <ReplyInterpretations>
            <DtcsCleared>
                <Boolean>
                    <Byte input_index="0" mask="0xFF" compare="0x03"/>
                </Boolean>
            </DtcsCleared>

            <EngineType>
                <String>
                    <Substring format="%8s">
                        <chars input_index="0" mask="0xFF" length="8"/>
                    </Substring>
                </String>
            </EngineType>

            <HistoryCleared>
                <Boolean>
                    <Byte1 input_index="0" mask="0xFF" compare="0x02"/>
                </Boolean>
            </HistoryCleared>

            <TransmissionType>
                <String>
                    <Substring format="%8s">
                        <chars input_index="8" mask="0xFF" length="8"/>
                    </Substring>
                </String>
            </TransmissionType>

            <TireRadius>
                <Float scale="0.01" offset="0">
                    <Integer type="unsigned" scale="1" offset="0">
                        <Byte1 input_index="16" mask="0xFF" output_index="1"/>
                        <Byte2 input_index="17" mask="0xFF" output_index="0"/>
                    </Integer>
                </Float>
            </TireRadius>

            <FinalGearRatio>
                <Float scale="0.001" offset="0">
                    <Integer type="unsigned" scale="1" offset="0">
                        <Byte1 input_index="18" mask="0xFF" output_index="1"/>
                        <Byte2 input_index="19" mask="0xFF" output_index="0"/>
                    </Integer>
                </Float>
            </FinalGearRatio>

            <DealerArea>
                <String>
                    <Substring format="%80s">
                        <chars input_index="20" mask="0xFF" length="80"/>
                    </Substring>
                </String>
            </DealerArea>

            <Vin>
                <String>
                    <Substring format="%20s">
                        <chars input_index="100" mask="0xFF" length="20"/>
                    </Substring>
                </String>
            </Vin>

            <FuelEconomyInterp>
                <Float scale="1" offset="0">
                    <Integer type="unsigned" scale="1" offset="0">
                        <Byte1 input_index="2" mask="0xFF" output_index="3"/>
                        <Byte2 input_index="3" mask="0xFF" output_index="2"/>
                        <Byte3 input_index="4" mask="0xFF" output_index="1"/>
                        <Byte4 input_index="5" mask="0xFF" output_index="0"/>
                    </Integer>
                </Float>
            </FuelEconomyInterp>

            <TotalMileageInterp>
                <Float scale="1" offset="0">
                    <Integer type="unsigned" scale="1" offset="0">
                        <Byte1 input_index="2" mask="0xFF" output_index="3"/>
                        <Byte2 input_index="3" mask="0xFF" output_index="2"/>
                        <Byte3 input_index="4" mask="0xFF" output_index="1"/>
                        <Byte4 input_index="5" mask="0xFF" output_index="0"/>
                    </Integer>
                </Float>
            </TotalMileageInterp>

            <DrmEngineInterp>
                <String>
                    <Substring format="%20s">
                        <chars input_index="02" mask="0xFF" length="20"/>
                    </Substring>
                </String>
            </DrmEngineInterp>

            <DrmAtInterp>
                <String>
                    <Substring format="%20s">
                        <chars input_index="02" mask="0xFF" length="20"/>
                    </Substring>
                </String>
            </DrmAtInterp>

            <DrmScrInterp>
                <String>
                    <Substring format="%20s">
                        <chars input_index="02" mask="0xFF" length="20"/>
                    </Substring>
                </String>
            </DrmScrInterp>

            <DrmBrakeInterp>
                <String>
                    <Substring format="%20s">
                        <chars input_index="02" mask="0xFF" length="20"/>
                    </Substring>
                </String>
            </DrmBrakeInterp>

            <DrmEdrOilTempInterp>
                <String>
                    <Substring format="%16s">
                        <chars input_index="02" mask="0xFF" length="16"/>
                    </Substring>
                </String>
            </DrmEdrOilTempInterp>


        </ReplyInterpretations>

    </SerialMessages>
</MimamoriModule>
