<MimamoriFaults>
    <!-- System Status -->
    <SoftwareFailure Code="0001" Description="Software failure using Mimamori module interface"/>

    <!-- Test Condition Failures -->
    <TimeoutFailure Code="0010" Description="Timeout waiting for test conditions"/>

    <!-- Communication Failures -->
    <CommunicationFailure Code="0015" Description="Mimamori Communication Failure"/>

    <!-- Test Failures -->
    <ModuleFaults Code="0020" Description="Mimamori Module Faults Present"/>
    <EDRNotCleared Code="0025" Description="Mimamori EDR Memory not cleared"/>
    <DRMNotCleared Code="0030" Description="Mimamori DRM Memory not cleared"/>
    <HistoryNotCleared Code="0035" Description="Mimamori History not cleared"/>
    <TotalMileageNotCleared Code="0040" Description="Mimamori Total Mileage not cleared"/>
	<FuelEconomyNotCleared Code="0045" Description="Mimamori Fuel Economy not cleared"/>
    
	<!-- Module Faults -->
	<ModuleFault_901845 Code="B1018_45" Description="ECU flash fault" />
	<ModuleFault_901844 Code="B1018_44" Description="ECU fault" />
	<ModuleFault_901855 Code="B1018_55" Description="EOL data fault" />
	<ModuleFault_C02800 Code="U0028_00" Description="CAN(J1939_CAN) communication error" />
	<ModuleFault_C03700 Code="U0037_00" Description="CAN(ISO_CAN) communication error" />
	<ModuleFault_C03700 Code="U0037_00" Description="CAN(ISO_CAN) communication error" />
	<ModuleFault_C10000 Code="U0100_00" Description="ECM communication fault" />
	<ModuleFault_C10100 Code="U0101_00" Description="Smoother/TCM/ACT communication fault" />
	<ModuleFault_C10C00 Code="U010C_00" Description="Turbo Controller communication fault" />
	<ModuleFault_C10E00 Code="U010E_00" Description="SCR ECU communication fault" />
	<ModuleFault_C12600 Code="U0126_00" Description="SAS communication fault" />
	<ModuleFault_C12900 Code="U0129_00" Description="Brake System ECU communication fault" />
	<ModuleFault_C13200 Code="U0132_00" Description="Air suspension ECU communication fault" />
	<ModuleFault_C14000 Code="U0140_00" Description="BCM communication fault" />
	<ModuleFault_C15100 Code="U0151_00" Description="SRS communication fault" />
	<ModuleFault_C15500 Code="U0155_00" Description="Multi_display ECU communication fault" />
	<ModuleFault_D00000 Code="U1000_00" Description="Base vehicle control ECU communication fault" />
	<ModuleFault_D00200 Code="U1002_00" Description="Idling Stop and Start ECU communication fault" />
	<ModuleFault_D00300 Code="U1003_00" Description="HSA communication fault" />
	<ModuleFault_D00400 Code="U1004_00" Description="VAT ECU communication fault" />
	<ModuleFault_D00500 Code="U1005_00" Description="BLS communication fault" />    
   
  
</MimamoriFaults>
